pandakeeper/__init__.py
pandakeeper/dataloader/__init__.py
pandakeeper/dataloader/core.py
pandakeeper/dataloader/sql/__init__.py
pandakeeper/dataloader/sql/core.py
pandakeeper/dataprocessor/__init__.py
pandakeeper/dataprocessor/cacher.py
pandakeeper/dataprocessor/core.py
pandakeeper/errors.py
pandakeeper/node.py
pandakeeper/py.typed
pandakeeper/typing.py
pandakeeper/validators.py
pandakeeper-0.0.29.dist-info/LICENSE
pandakeeper-0.0.29.dist-info/WHEEL
pandakeeper-0.0.29.dist-info/METADATA
pandakeeper-0.0.29.dist-info/RECORD
